<?xml version="1.0" encoding="utf-8"?>
<odoo>
    <data>
        <record id="attendance_faculty_demo_data_1" model="attendance.faculty">
            <field name="name">Hardik</field>
            <field name="email">hardik@gamil.com</field>
        </record>
        <record id="attendance_faculty_demo_data_2" model="attendance.faculty">
            <field name="name">Priyal</field>
            <field name="email">Priyal@gamil.com</field>
        </record>
        <record id="attendance_faculty_demo_data_3" model="attendance.faculty">
            <field name="name">Harshil</field>
            <field name="email">Harshil@gamil.com</field>
        </record>
        <record id="attendance_faculty_demo_data_4" model="attendance.faculty">
            <field name="name">Neha</field>
            <field name="email">Neha@gamil.com</field>
        </record>
        <record id="attendance_faculty_demo_data_5" model="attendance.faculty">
            <field name="name">Nilesh</field>
            <field name="email">Nilesh@gamil.com</field>
        </record>
    </data>
</odoo>
            